polyclean/__init__.py
polyclean/polyclean.py
polyclean/scratch.py
polyclean-0.1.9.dist-info/LICENSE
polyclean-0.1.9.dist-info/METADATA
polyclean-0.1.9.dist-info/WHEEL
polyclean-0.1.9.dist-info/top_level.txt
polyclean-0.1.9.dist-info/RECORD
